gitfilesplit/__init__.py
gitfilesplit/cli.py
gitfilesplit/toolbox.py
gitfilesplit-1.0.0.dist-info/AUTHORS
gitfilesplit-1.0.0.dist-info/LICENSE
gitfilesplit-1.0.0.dist-info/METADATA
gitfilesplit-1.0.0.dist-info/WHEEL
gitfilesplit-1.0.0.dist-info/entry_points.txt
gitfilesplit-1.0.0.dist-info/top_level.txt
gitfilesplit-1.0.0.dist-info/RECORD
